{"nodes": [{"id": "auth", "label": "Auth", "file_type": "code", "source_file": "src/pages/Auth.jsx", "source_location": null, "source_url": null, "captured_at": null, "author": null, "contributor": null}, {"id": "usenavigate", "label": "useNavigate", "file_type": "code", "source_file": "src/pages/Auth.jsx", "source_location": null, "source_url": null, "captured_at": null, "author": null, "contributor": null}, {"id": "errors", "label": "Errors", "file_type": "code", "source_file": "src/pages/Auth.jsx", "source_location": null, "source_url": null, "captured_at": null, "author": null, "contributor": null}, {"id": "userprofile", "label": "UserProfile", "file_type": "code", "source_file": "src/pages/Auth.jsx", "source_location": null, "source_url": null, "captured_at": null, "author": null, "contributor": null}, {"id": "authsuccess", "label": "AuthSuccess", "file_type": "code", "source_file": "src/pages/Auth.jsx", "source_location": null, "source_url": null, "captured_at": null, "author": null, "contributor": null}, {"id": "withgoogle", "label": "WithGoogle", "file_type": "code", "source_file": "src/pages/Auth.jsx", "source_location": null, "source_url": null, "captured_at": null, "author": null, "contributor": null}, {"id": "activetab", "label": "ActiveTab", "file_type": "code", "source_file": "src/pages/Auth.jsx", "source_location": null, "source_url": null, "captured_at": null, "author": null, "contributor": null}, {"id": "name", "label": "Name", "file_type": "code", "source_file": "src/pages/Auth.jsx", "source_location": null, "source_url": null, "captured_at": null, "author": null, "contributor": null}, {"id": "email", "label": "Email", "file_type": "code", "source_file": "src/pages/Auth.jsx", "source_location": null, "source_url": null, "captured_at": null, "author": null, "contributor": null}, {"id": "password", "label": "Password", "file_type": "code", "source_file": "src/pages/Auth.jsx", "source_location": null, "source_url": null, "captured_at": null, "author": null, "contributor": null}, {"id": "confirmpassword", "label": "ConfirmPassword", "file_type": "code", "source_file": "src/pages/Auth.jsx", "source_location": null, "source_url": null, "captured_at": null, "author": null, "contributor": null}], "edges": [{"source": "auth", "target": "authcontext", "relation": "references", "confidence": "EXTRACTED", "confidence_score": 1, "source_file": "src/pages/Auth.jsx", "source_location": null, "weight": 1}, {"source": "auth", "target": "firestore", "relation": "references", "confidence": "EXTRACTED", "confidence_score": 1, "source_file": "src/pages/Auth.jsx", "source_location": null, "weight": 1}, {"source": "auth", "target": "button", "relation": "references", "confidence": "EXTRACTED", "confidence_score": 1, "source_file": "src/pages/Auth.jsx", "source_location": null, "weight": 1}, {"source": "auth", "target": "input", "relation": "references", "confidence": "EXTRACTED", "confidence_score": 1, "source_file": "src/pages/Auth.jsx", "source_location": null, "weight": 1}, {"source": "auth", "target": "usestate", "relation": "calls", "confidence": "EXTRACTED", "confidence_score": 1, "source_file": "src/pages/Auth.jsx", "source_location": null, "weight": 1}, {"source": "auth", "target": "useauth", "relation": "calls", "confidence": "EXTRACTED", "confidence_score": 1, "source_file": "src/pages/Auth.jsx", "source_location": null, "weight": 1}, {"source": "auth", "target": "usenavigate", "relation": "calls", "confidence": "EXTRACTED", "confidence_score": 1, "source_file": "src/pages/Auth.jsx", "source_location": null, "weight": 1}, {"source": "auth", "target": "errors", "relation": "calls", "confidence": "EXTRACTED", "confidence_score": 1, "source_file": "src/pages/Auth.jsx", "source_location": null, "weight": 1}, {"source": "auth", "target": "userprofile", "relation": "calls", "confidence": "EXTRACTED", "confidence_score": 1, "source_file": "src/pages/Auth.jsx", "source_location": null, "weight": 1}, {"source": "auth", "target": "default", "relation": "calls", "confidence": "EXTRACTED", "confidence_score": 1, "source_file": "src/pages/Auth.jsx", "source_location": null, "weight": 1}, {"source": "auth", "target": "loading", "relation": "calls", "confidence": "EXTRACTED", "confidence_score": 1, "source_file": "src/pages/Auth.jsx", "source_location": null, "weight": 1}, {"source": "auth", "target": "authsuccess", "relation": "calls", "confidence": "EXTRACTED", "confidence_score": 1, "source_file": "src/pages/Auth.jsx", "source_location": null, "weight": 1}, {"source": "auth", "target": "withgoogle", "relation": "calls", "confidence": "EXTRACTED", "confidence_score": 1, "source_file": "src/pages/Auth.jsx", "source_location": null, "weight": 1}, {"source": "auth", "target": "activetab", "relation": "calls", "confidence": "EXTRACTED", "confidence_score": 1, "source_file": "src/pages/Auth.jsx", "source_location": null, "weight": 1}, {"source": "auth", "target": "name", "relation": "calls", "confidence": "EXTRACTED", "confidence_score": 1, "source_file": "src/pages/Auth.jsx", "source_location": null, "weight": 1}, {"source": "auth", "target": "email", "relation": "calls", "confidence": "EXTRACTED", "confidence_score": 1, "source_file": "src/pages/Auth.jsx", "source_location": null, "weight": 1}, {"source": "auth", "target": "password", "relation": "calls", "confidence": "EXTRACTED", "confidence_score": 1, "source_file": "src/pages/Auth.jsx", "source_location": null, "weight": 1}, {"source": "auth", "target": "confirmpassword", "relation": "calls", "confidence": "EXTRACTED", "confidence_score": 1, "source_file": "src/pages/Auth.jsx", "source_location": null, "weight": 1}], "hyperedges": []}