{"nodes": [{"id": "home_user_site_readme_md", "label": "README.md", "file_type": "document", "source_file": "/home/user/site/README.md", "source_location": "L1"}, {"id": "site_readme_about_the_project", "label": "\ud83d\udcd6 About The Project", "file_type": "document", "source_file": "/home/user/site/README.md", "source_location": "L17"}, {"id": "site_readme_tech_stack", "label": "\ud83d\ude80 Tech Stack", "file_type": "document", "source_file": "/home/user/site/README.md", "source_location": "L25"}, {"id": "site_readme_design_system_eco_cosmos", "label": "\ud83c\udfa8 Design System: \"Eco Cosmos\"", "file_type": "document", "source_file": "/home/user/site/README.md", "source_location": "L41"}, {"id": "site_readme_key_features", "label": "\ud83c\udfc6 Key Features", "file_type": "document", "source_file": "/home/user/site/README.md", "source_location": "L55"}, {"id": "site_readme_project_structure", "label": "\ud83d\udee0\ufe0f Project Structure", "file_type": "document", "source_file": "/home/user/site/README.md", "source_location": "L65"}, {"id": "site_readme_local_setup_installation", "label": "\ud83d\udce6 Local Setup & Installation", "file_type": "document", "source_file": "/home/user/site/README.md", "source_location": "L93"}, {"id": "site_readme_1_configure_environment_variables", "label": "1. Configure Environment Variables", "file_type": "document", "source_file": "/home/user/site/README.md", "source_location": "L95"}, {"id": "site_readme_2_install_dependencies", "label": "2. Install Dependencies", "file_type": "document", "source_file": "/home/user/site/README.md", "source_location": "L107"}, {"id": "site_readme_3_run_locally_dev_mode", "label": "3. Run Locally (Dev Mode)", "file_type": "document", "source_file": "/home/user/site/README.md", "source_location": "L112"}, {"id": "site_readme_4_build_for_production", "label": "4. Build for Production", "file_type": "document", "source_file": "/home/user/site/README.md", "source_location": "L117"}], "edges": [{"source": "home_user_site_readme_md", "target": "site_readme_about_the_project", "relation": "contains", "confidence": "EXTRACTED", "source_file": "/home/user/site/README.md", "source_location": "L17", "weight": 1.0}, {"source": "home_user_site_readme_md", "target": "site_readme_tech_stack", "relation": "contains", "confidence": "EXTRACTED", "source_file": "/home/user/site/README.md", "source_location": "L25", "weight": 1.0}, {"source": "home_user_site_readme_md", "target": "site_readme_design_system_eco_cosmos", "relation": "contains", "confidence": "EXTRACTED", "source_file": "/home/user/site/README.md", "source_location": "L41", "weight": 1.0}, {"source": "home_user_site_readme_md", "target": "site_readme_key_features", "relation": "contains", "confidence": "EXTRACTED", "source_file": "/home/user/site/README.md", "source_location": "L55", "weight": 1.0}, {"source": "home_user_site_readme_md", "target": "site_readme_project_structure", "relation": "contains", "confidence": "EXTRACTED", "source_file": "/home/user/site/README.md", "source_location": "L65", "weight": 1.0}, {"source": "home_user_site_readme_md", "target": "site_readme_local_setup_installation", "relation": "contains", "confidence": "EXTRACTED", "source_file": "/home/user/site/README.md", "source_location": "L93", "weight": 1.0}, {"source": "site_readme_local_setup_installation", "target": "site_readme_1_configure_environment_variables", "relation": "contains", "confidence": "EXTRACTED", "source_file": "/home/user/site/README.md", "source_location": "L95", "weight": 1.0}, {"source": "site_readme_local_setup_installation", "target": "site_readme_2_install_dependencies", "relation": "contains", "confidence": "EXTRACTED", "source_file": "/home/user/site/README.md", "source_location": "L107", "weight": 1.0}, {"source": "site_readme_local_setup_installation", "target": "site_readme_3_run_locally_dev_mode", "relation": "contains", "confidence": "EXTRACTED", "source_file": "/home/user/site/README.md", "source_location": "L112", "weight": 1.0}, {"source": "site_readme_local_setup_installation", "target": "site_readme_4_build_for_production", "relation": "contains", "confidence": "EXTRACTED", "source_file": "/home/user/site/README.md", "source_location": "L117", "weight": 1.0}], "input_tokens": 0, "output_tokens": 0}